spcli_ui/menu.py
spcli_ui/sp_api.py
spcli_ui/spui.py
pyspcli_ui-0.1.0.dist-info/LICENSE
pyspcli_ui-0.1.0.dist-info/METADATA
pyspcli_ui-0.1.0.dist-info/WHEEL
pyspcli_ui-0.1.0.dist-info/entry_points.txt
pyspcli_ui-0.1.0.dist-info/top_level.txt
pyspcli_ui-0.1.0.dist-info/RECORD
