Metadata-Version: 2.1
Name: pyspcli-ui
Version: 0.1.0
Summary: Terminal User Interface for spcli
Home-page: https://github.com/ipHeaders/spcli-ui
Author: IP Headers.llc
Author-email: kentik.hanzo94@gmail.com
Project-URL: Bug Tracker, https://github.com/ipHeaders/spcli-ui/issues
Project-URL: Code of Conduct, https://github.com/ipHeaders/spcli-ui/blob/main/CODE_OF_CONDUCT.md
Project-URL: Source Code, https://github.com/ipHeaders/spcli-ui
Classifier: Intended Audience :: Developers
Classifier: Intended Audience :: Information Technology
Classifier: Intended Audience :: System Administrators
Classifier: Natural Language :: English
Classifier: Programming Language :: Python :: 3
Classifier: Programming Language :: Python :: 3.7
Classifier: Programming Language :: Python :: 3.8
Classifier: Programming Language :: Python :: 3.9
Classifier: Programming Language :: Python :: 3.10
Classifier: Programming Language :: Python :: 3.11
Classifier: Programming Language :: Python :: 3 :: Only
Requires-Python: >=3.7, <4
License-File: LICENSE
Requires-Dist: pyspcli
Requires-Dist: simple-term-menu (==1.5.0)
